msanalyst/__init__.py
msanalyst/main.py
msanalyst/mn_merging.py
msanalyst/ms1search.py
msanalyst/ms2Search.py
msanalyst/re_networking.py
msanalyst/my_packages/__init__.py
msanalyst/my_packages/cheminfo_tools.py
msanalyst/my_packages/config.py
msanalyst/my_packages/functions.py
msanalyst/my_packages/ms2tools.py
msanalyst/my_packages/ms2visualization.py
msanalyst/my_packages/ms2visualization_ver2.py
msanalyst/my_packages/peaktools.py
msanalyst/my_packages/plot.py
msanalyst/my_packages/significance.py
msanalyst/my_packages/spectrum_alignment.py
msanalyst-0.2.0.dist-info/METADATA
msanalyst-0.2.0.dist-info/WHEEL
msanalyst-0.2.0.dist-info/entry_points.txt
msanalyst-0.2.0.dist-info/top_level.txt
msanalyst-0.2.0.dist-info/RECORD
